{
    "id": "tt0160127",
    "name": "Charlie's Angels",
    "description": "The captivating crime-fighting trio who are the masters of disguise, espionage, and martial arts. When a devious mastermind embroils them in a plot to destroy individual privacy, the Angels, aided by their loyal sidekick Bosley (Bill Murray), set out to bring down the bad guys. But when a terrible secret is revealed, it makes the Angels targets for assassination.\u2014Anthony Pereyra {hypersonic91@yahoo.com}",
    "genre": "Action, Adventure, Comedy",
    "imageUrl": "https://m.media-amazon.com/images/M/MV5BMGI1NTM5MTItNDcxMS00YTIwLTg1NjUtNzE5ZGE5NDkxMmU4XkEyXkFqcGdeQXVyMTQxNzMzNDI@._V1_QL75_UX380_CR0,6,380,562_.jpg",
    "rate": "5.6"
}