{
    "id": "tt1483013",
    "name": "Oblivion",
    "description": "One of the few remaining drone repairmen assigned to Earth, its surface devastated after decades of war with the alien Scavs, discovers a crashed spacecraft with contents that bring into question everything he believed about the war, and may even put the fate of mankind in his hands.\u2014Black Dahlia",
    "genre": "Action, Adventure, Sci-Fi",
    "imageUrl": "https://m.media-amazon.com/images/M/MV5BYmNmNTUzNDYtNDFjZS00YThjLWI4ODUtMTJhM2I1NzQ3MzRlXkEyXkFqcGdeQXVyMTM1MDExOTE2._V1_QL75_UY281_CR3,0,190,281_.jpg",
    "rate": "7.0"
}