{
    "id": "tt0379786",
    "name": "Serenity",
    "description": "Serenity continues the story of the TV series it was based upon (\"Firefly\"). River Tam had a secret - one in which she's not even aware - so dangerous, no one's safe, as an Alliance operative's sent to capture her, and all others are considered irrelevant to his job.\u2014Anthony Pereyra {hypersonic91@yahoo.com}",
    "genre": "Action, Adventure, Sci-Fi",
    "imageUrl": "https://m.media-amazon.com/images/M/MV5BMTc5YjQ0MGQtOTdjZS00OGZhLTk1ZGItMThjOGFiZmMxYWRjL2ltYWdlL2ltYWdlXkEyXkFqcGdeQXVyMTQxNzMzNDI@._V1_QL75_UX380_CR0,0,380,562_.jpg",
    "rate": "7.8"
}