{
    "id": "tt0482571",
    "name": "The Prestige",
    "description": "Set in London in the 1800s, two rival magicians read each others diary containing the secrets of their magic tricks and personal life. As we go back in time when the diaries were written, both magicians become obsessed with their rival's best trick. The tricks, as shown to the audience, look the same, but neither magician can figure out how his opponent does it.\u2014gary",
    "genre": "Drama, Mystery, Sci-Fi",
    "imageUrl": "https://m.media-amazon.com/images/M/MV5BMzZhOTVmOTEtZGIxZS00MmExLTk1OWItOTFhMzNjNzNiN2M4XkEyXkFqcGdeQXVyOTU2NDAzNDE@._V1_QL75_UY281_CR11,0,190,281_.jpg",
    "rate": "8.5"
}